<?xml version="1.0" encoding="utf-8"?>
<ArrayOfSale xmlns:xsi="http://www.w3.org/2001/XMLSchema-instance" xmlns:xsd="http://www.w3.org/2001/XMLSchema">
  <Sale>
    <IdSale>522</IdSale>
    <IdProductOfSale>113</IdProductOfSale>
    <AmountToGetSale>1</AmountToGetSale>
    <SumPrice>4500</SumPrice>
    <IsForAllCustomers>true</IsForAllCustomers>
    <StartSale>2025-05-18T18:38:34.363</StartSale>
    <EndSale>2025-06-01T18:38:34.361</EndSale>
  </Sale>
  <Sale>
    <IdSale>524</IdSale>
    <IdProductOfSale>113</IdProductOfSale>
    <AmountToGetSale>1</AmountToGetSale>
    <SumPrice>4800</SumPrice>
    <IsForAllCustomers>false</IsForAllCustomers>
    <StartSale>2025-05-21T18:48:46.9301779+03:00</StartSale>
    <EndSale>2025-05-21T18:48:46.9278694+03:00</EndSale>
  </Sale>
  <Sale>
    <IdSale>525</IdSale>
    <IdProductOfSale>118</IdProductOfSale>
    <AmountToGetSale>2</AmountToGetSale>
    <SumPrice>5</SumPrice>
    <IsForAllCustomers>false</IsForAllCustomers>
    <StartSale>2025-05-18T18:57:50.913</StartSale>
    <EndSale>2025-05-30T18:57:50.911</EndSale>
  </Sale>
  <Sale>
    <IdSale>526</IdSale>
    <IdProductOfSale>118</IdProductOfSale>
    <AmountToGetSale>3</AmountToGetSale>
    <SumPrice>10</SumPrice>
    <IsForAllCustomers>true</IsForAllCustomers>
    <StartSale>2025-05-24T20:23:59.003</StartSale>
    <EndSale>2025-05-31T20:23:58.998</EndSale>
  </Sale>
</ArrayOfSale>